<?xml version="1.0" encoding="UTF-8"?>
<!DOCTYPE mapper PUBLIC "-//mybatis.org//DTD Mapper 3.0//EN" "http://mybatis.org/dtd/mybatis-3-mapper.dtd">
<mapper namespace="com.example.shop.dao.ProductsMapper">
  <resultMap id="BaseResultMap" type="com.example.shop.service.vo.Products">
    <!--
      WARNING - @mbg.generated
      This element is automatically generated by MyBatis Generator, do not modify.
      This element was generated on Fri May 23 12:39:59 CST 2025.
    -->
    <id column="id" jdbcType="BIGINT" property="id" />
    <result column="name" jdbcType="VARCHAR" property="name" />
    <result column="price" jdbcType="DECIMAL" property="price" />
    <result column="stock" jdbcType="INTEGER" property="stock" />
    <result column="image_url" jdbcType="VARCHAR" property="imageUrl" />
    <result column="category" jdbcType="VARCHAR" property="category" />
    <result column="created_at" jdbcType="TIMESTAMP" property="createdAt" />
    <result column="description" jdbcType="LONGVARCHAR" property="description" />
  </resultMap>
  <delete id="deleteByPrimaryKey" parameterType="java.lang.Long">
    <!--
      WARNING - @mbg.generated
      This element is automatically generated by MyBatis Generator, do not modify.
      This element was generated on Fri May 23 12:39:59 CST 2025.
    -->
    delete from products
    where id = #{id,jdbcType=BIGINT}
  </delete>
  <insert id="insert" keyColumn="id" keyProperty="id" parameterType="com.example.shop.service.vo.Products" useGeneratedKeys="true">
    <!--
      WARNING - @mbg.generated
      This element is automatically generated by MyBatis Generator, do not modify.
      This element was generated on Fri May 23 12:39:59 CST 2025.
    -->
    insert into products (name, price, stock, 
      image_url, category, created_at, 
      description)
    values (#{name,jdbcType=VARCHAR}, #{price,jdbcType=DECIMAL}, #{stock,jdbcType=INTEGER}, 
      #{imageUrl,jdbcType=VARCHAR}, #{category,jdbcType=VARCHAR}, #{createdAt,jdbcType=TIMESTAMP}, 
      #{description,jdbcType=LONGVARCHAR})
  </insert>
  <update id="updateByPrimaryKey" parameterType="com.example.shop.service.vo.Products">
    <!--
      WARNING - @mbg.generated
      This element is automatically generated by MyBatis Generator, do not modify.
      This element was generated on Fri May 23 12:39:59 CST 2025.
    -->
    update products
    set name = #{name,jdbcType=VARCHAR},
      price = #{price,jdbcType=DECIMAL},
      stock = #{stock,jdbcType=INTEGER},
      image_url = #{imageUrl,jdbcType=VARCHAR},
      category = #{category,jdbcType=VARCHAR},
      created_at = #{createdAt,jdbcType=TIMESTAMP},
      description = #{description,jdbcType=LONGVARCHAR}
    where id = #{id,jdbcType=BIGINT}
  </update>
  <select id="selectByPrimaryKey" parameterType="java.lang.Long" resultMap="BaseResultMap">
    <!--
      WARNING - @mbg.generated
      This element is automatically generated by MyBatis Generator, do not modify.
      This element was generated on Fri May 23 12:39:59 CST 2025.
    -->
    select id, name, price, stock, image_url, category, created_at, description
    from products
    where id = #{id,jdbcType=BIGINT}
  </select>
  <select id="selectAll" resultMap="BaseResultMap">
    <!--
      WARNING - @mbg.generated
      This element is automatically generated by MyBatis Generator, do not modify.
      This element was generated on Fri May 23 12:39:59 CST 2025.
    -->
    select id, name, price, stock, image_url, category, created_at, description
    from products
  </select>
</mapper>